name2gender/__init__.py
name2gender/__main__.py
name2gender/_entry_point.py
name2gender/model.py
name2gender-0.0.5.dist-info/licenses/LICENSE
name2gender-0.0.5.dist-info/METADATA
name2gender-0.0.5.dist-info/WHEEL
name2gender-0.0.5.dist-info/entry_points.txt
name2gender-0.0.5.dist-info/top_level.txt
name2gender-0.0.5.dist-info/RECORD
