Metadata-Version: 2.4
Name: name2gender
Version: 0.0.5
Summary: From names in multiple languages to genders.
Requires-Python: >=3.10
License-File: LICENSE
Requires-Dist: deeplotx>=0.9.9
Requires-Dist: name4py>=0.1.4
Requires-Dist: gdown
Requires-Dist: requests
Requires-Dist: click
Dynamic: license-file
